[
  {
    "sn": "2555GJ26",
    "login": {
      "username": "paddlebuck",
      "pass": "AM/fd!E%wA~zbgm8",
      "email": "bernice@hotmail.com"
    },
    "title": "Master",
    "fname": "Norma",
    "lname": "Hildring",
    "photo": "https://randomuser.me/api/portraits/men/87.jpg",
    "orders": [
      {
        "ord_sn": "oid_6173AG44",
        "product": [
          {
            "prod_sn": "prid_5047SQ29",
            "product": "Rank Tough",
            "productBrand": "McDonald's"
          },
          {
            "prod_sn": "prid_9210SS45",
            "product": "Zamtip",
            "productBrand": "Adobe"
          },
          {
            "prod_sn": "prid_9768YP46",
            "product": "U-lux",
            "productBrand": "Chevrolet"
          }
        ],
        "orderType": "couch",
        "amount": 309
      },
      {
        "ord_sn": "oid_9228FN06",
        "product": [
          {
            "prod_sn": "prid_7529WV28",
            "product": "Isdox",
            "productBrand": "BMW"
          },
          {
            "prod_sn": "prid_3817ZB86",
            "product": "Kinhold",
            "productBrand": "Wells Fargo"
          },
          {
            "prod_sn": "prid_1743QA85",
            "product": "Rank Joyla",
            "productBrand": "Gillette"
          }
        ],
        "orderType": "door",
        "amount": 369
      },
      {
        "ord_sn": "oid_0847SU15",
        "product": [
          {
            "prod_sn": "prid_7439QQ77",
            "product": "It Lex",
            "productBrand": "Telecom"
          },
          {
            "prod_sn": "prid_0743MA58",
            "product": "Kinlab",
            "productBrand": "Corona"
          },
          {
            "prod_sn": "prid_5637VQ77",
            "product": "Is Lux",
            "productBrand": "Costco"
          }
        ],
        "orderType": "twezzers",
        "amount": 354
      },
      {
        "ord_sn": "oid_5777FO06",
        "product": [
          {
            "prod_sn": "prid_4867JP49",
            "product": "Dalttom",
            "productBrand": "Sony"
          },
          {
            "prod_sn": "prid_0481JY89",
            "product": "Kinlab",
            "productBrand": "Automotive"
          },
          {
            "prod_sn": "prid_8324WA87",
            "product": "Vilatough",
            "productBrand": "Wells Fargo"
          }
        ],
        "orderType": "leg warmers",
        "amount": 463
      }
    ],
    "phones": {
      "home": "828-77009",
      "mobile": "01648-19053236"
    },
    "address": {
      "personal": {
        "street": "Bacon Terrace",
        "city": "Rosario",
        "pcode": 60658,
        "country": "Virgin Islands (U.S.)"
      },
      "work": {
        "workplace": "Bioholding Inc.",
        "jobtitle": "Teacher Assistant",
        "street": "Birchbrook Avenue",
        "city": "Changshu",
        "pcode": 16654,
        "country": "Peru",
        "workPhone": "861-22025"
      }
    },
    "about": [
      "coast",
      "toy",
      "productive",
      "fascinated",
      "daughter",
      "ticket",
      "befitting",
      "terrific"
    ],
    "customId": "custId-3117CA15-kn",
    "special": "This value will be returns as is."
  },
  {
    "sn": "6446DI63",
    "login": {
      "username": "loanstud",
      "pass": "KiMrf!Aj+*/s!91G",
      "email": "morgan.knoch@mail.com"
    },
    "title": "Madam",
    "fname": "Blythe",
    "lname": "Sayyed",
    "photo": "https://randomuser.me/api/portraits/men/67.jpg",
    "orders": [
      {
        "ord_sn": "oid_5075RN55",
        "product": [
          {
            "prod_sn": "prid_9146HE59",
            "product": "K-home",
            "productBrand": "Bank of America"
          },
          {
            "prod_sn": "prid_6506AK49",
            "product": "Triofresh",
            "productBrand": "Apple"
          },
          {
            "prod_sn": "prid_9001OJ90",
            "product": "Goldencof",
            "productBrand": "Pampers"
          }
        ],
        "orderType": "floor",
        "amount": 383
      },
      {
        "ord_sn": "oid_1592PL09",
        "product": [
          {
            "prod_sn": "prid_8979OW36",
            "product": "Tres Sing",
            "productBrand": "Uniqlo"
          },
          {
            "prod_sn": "prid_2784BM58",
            "product": "Lam Hotwarm",
            "productBrand": "Siemens"
          },
          {
            "prod_sn": "prid_1939WB94",
            "product": "Villa-Flex",
            "productBrand": "Facebook"
          }
        ],
        "orderType": "lamp shade",
        "amount": 301
      },
      {
        "ord_sn": "oid_4051DQ91",
        "product": [
          {
            "prod_sn": "prid_2490MK21",
            "product": "Tripplestock",
            "productBrand": "Microsoft"
          },
          {
            "prod_sn": "prid_6109KP66",
            "product": "K-lax",
            "productBrand": "Sony"
          },
          {
            "prod_sn": "prid_1577ZD24",
            "product": "Dongtrax",
            "productBrand": "Telecom"
          }
        ],
        "orderType": "sticky note",
        "amount": 454
      },
      {
        "ord_sn": "oid_5456VB64",
        "product": [
          {
            "prod_sn": "prid_0071OQ30",
            "product": "Joyron",
            "productBrand": "Budweiser"
          },
          {
            "prod_sn": "prid_2079WG15",
            "product": "Tran Lux",
            "productBrand": "BMW"
          },
          {
            "prod_sn": "prid_5614RQ85",
            "product": "Bionix",
            "productBrand": "Fox"
          }
        ],
        "orderType": "food",
        "amount": 389
      }
    ],
    "phones": {
      "home": "663-30885",
      "mobile": "01554-12208030"
    },
    "address": {
      "personal": {
        "street": "Irish Court",
        "city": "Nay Pyi Taw",
        "pcode": 85096,
        "country": "Madagascar"
      },
      "work": {
        "workplace": "Rantouch and Partners",
        "jobtitle": "Podiatrist",
        "street": "Mayo Court",
        "city": "Hamhung",
        "pcode": 37223,
        "country": "Western Sahara",
        "workPhone": "820-13035"
      }
    },
    "about": [
      "injure",
      "mountainous",
      "wine",
      "naive",
      "smoke",
      "noiseless",
      "quixotic",
      "sense"
    ],
    "customId": "custId-7444IB56-by",
    "special": "This value will be returns as is."
  },
  {
    "sn": "5865AQ25",
    "login": {
      "username": "ettenmoorscoyote",
      "pass": "iAJP-Sgqo#y5?Ffc",
      "email": "sterling@gmail.com"
    },
    "title": "Mr.",
    "fname": "Maude",
    "lname": "Damerell",
    "photo": "https://randomuser.me/api/portraits/men/01.jpg",
    "orders": [
      {
        "ord_sn": "oid_4394CR48",
        "product": [
          {
            "prod_sn": "prid_3909ET27",
            "product": "Lexitone",
            "productBrand": "IBM"
          },
          {
            "prod_sn": "prid_3104CA93",
            "product": "Stronging",
            "productBrand": "NIKE"
          },
          {
            "prod_sn": "prid_2391YS40",
            "product": "K-sing",
            "productBrand": "Apple"
          }
        ],
        "orderType": "air freshener",
        "amount": 371
      },
      {
        "ord_sn": "oid_5725ZG72",
        "product": [
          {
            "prod_sn": "prid_9092OL35",
            "product": "Ozer-Nix",
            "productBrand": "IBM"
          },
          {
            "prod_sn": "prid_9214UI64",
            "product": "Quadlux",
            "productBrand": "Coca-Cola"
          },
          {
            "prod_sn": "prid_6930IV84",
            "product": "Staning",
            "productBrand": "Fox"
          }
        ],
        "orderType": "sun glasses",
        "amount": 421
      },
      {
        "ord_sn": "oid_4519HV84",
        "product": [
          {
            "prod_sn": "prid_3325AK80",
            "product": "Silremtex",
            "productBrand": "Oracle"
          },
          {
            "prod_sn": "prid_2973CB00",
            "product": "Kaneco",
            "productBrand": "Gucci"
          },
          {
            "prod_sn": "prid_7902NB80",
            "product": "Zumlex",
            "productBrand": "Honda"
          }
        ],
        "orderType": "toothbrush",
        "amount": 395
      },
      {
        "ord_sn": "oid_5287HH46",
        "product": [
          {
            "prod_sn": "prid_5783RU93",
            "product": "Singledonphase",
            "productBrand": "Budweiser"
          },
          {
            "prod_sn": "prid_5611CX54",
            "product": "Sing Zuntrax",
            "productBrand": "Visa"
          },
          {
            "prod_sn": "prid_8123MN24",
            "product": "Kandax",
            "productBrand": "Corona"
          }
        ],
        "orderType": "lamp",
        "amount": 339
      }
    ],
    "phones": {
      "home": "791-63678",
      "mobile": "01738-18056421"
    },
    "address": {
      "personal": {
        "street": "Melbourne Lane",
        "city": "Haikou",
        "pcode": 83284,
        "country": "Curaçao"
      },
      "work": {
        "workplace": "Cancity Enterprise Corp.",
        "jobtitle": "Administrative Assistant",
        "street": "Iiams Court",
        "city": "Samara",
        "pcode": 66481,
        "country": "Gibraltar",
        "workPhone": "106-60151"
      }
    },
    "about": [
      "science",
      "price",
      "sparkling"
    ],
    "customId": "custId-2365HE00-zz",
    "special": "This value will be returns as is."
  },
  {
    "sn": "9124AV30",
    "login": {
      "username": "besmirchimminent",
      "pass": "z$*h?q/7?H6#J~2i",
      "email": "moneybagtrouble@live.com"
    },
    "title": "Master",
    "fname": "Emilie",
    "lname": "Taubert",
    "photo": "https://randomuser.me/api/portraits/men/92.jpg",
    "orders": [
      {
        "ord_sn": "oid_1608WH15",
        "product": [
          {
            "prod_sn": "prid_6953LB78",
            "product": "Plusstrong",
            "productBrand": "Automotive"
          },
          {
            "prod_sn": "prid_2202EA23",
            "product": "Openlab",
            "productBrand": "EY"
          },
          {
            "prod_sn": "prid_5233QR57",
            "product": "Statity",
            "productBrand": "Audi"
          }
        ],
        "orderType": "lace",
        "amount": 422
      },
      {
        "ord_sn": "oid_9404KG78",
        "product": [
          {
            "prod_sn": "prid_2427OT44",
            "product": "Jaystock",
            "productBrand": "Intel"
          },
          {
            "prod_sn": "prid_5974PG07",
            "product": "Opezozplus",
            "productBrand": "Allianz"
          },
          {
            "prod_sn": "prid_9852VC79",
            "product": "Strongdax",
            "productBrand": "Pampers"
          }
        ],
        "orderType": "fake flowers",
        "amount": 317
      },
      {
        "ord_sn": "oid_6128RZ90",
        "product": [
          {
            "prod_sn": "prid_4432UF75",
            "product": "Movetrax",
            "productBrand": "Huawei"
          },
          {
            "prod_sn": "prid_9127PJ49",
            "product": "Unaron",
            "productBrand": "Cisco"
          },
          {
            "prod_sn": "prid_9675EJ46",
            "product": "Solozennix",
            "productBrand": "CVS"
          }
        ],
        "orderType": "twezzers",
        "amount": 304
      },
      {
        "ord_sn": "oid_4014ZT94",
        "product": [
          {
            "prod_sn": "prid_1564YK45",
            "product": "Haydox",
            "productBrand": "NIKE"
          },
          {
            "prod_sn": "prid_0982WI94",
            "product": "Solozennix",
            "productBrand": "Deloitte"
          },
          {
            "prod_sn": "prid_2007BN98",
            "product": "Joyron",
            "productBrand": "SAP"
          }
        ],
        "orderType": "bracelet",
        "amount": 441
      }
    ],
    "phones": {
      "home": "299-67206",
      "mobile": "01764-15838926"
    },
    "address": {
      "personal": {
        "street": "Belcherry Loop",
        "city": "Chiang Rai",
        "pcode": 34497,
        "country": "Zambia"
      },
      "work": {
        "workplace": "Armstrong and Bruen",
        "jobtitle": "Nail Technician",
        "street": "Alandari Lane",
        "city": "Kunshan",
        "pcode": 97914,
        "country": "Ghana",
        "workPhone": "882-65899"
      }
    },
    "about": [
      "tender",
      "stitch",
      "relieved",
      "detect",
      "approve",
      "groovy"
    ],
    "customId": "custId-8498XZ11-fl",
    "special": "This value will be returns as is."
  },
  {
    "sn": "0698DO12",
    "login": {
      "username": "hithersteady",
      "pass": "$q+udByY%p0Z&n47",
      "email": "lyman@mail.com"
    },
    "title": "Master",
    "fname": "Linda",
    "lname": "Salter",
    "photo": "https://randomuser.me/api/portraits/men/49.jpg",
    "orders": [
      {
        "ord_sn": "oid_6026RT12",
        "product": [
          {
            "prod_sn": "prid_2584WK11",
            "product": "Faxlam",
            "productBrand": "Ebay"
          },
          {
            "prod_sn": "prid_5868KQ44",
            "product": "Sub-Lam",
            "productBrand": "Frito-Lay"
          },
          {
            "prod_sn": "prid_4772ZJ98",
            "product": "Hatin",
            "productBrand": "Dell"
          }
        ],
        "orderType": "drawer",
        "amount": 408
      },
      {
        "ord_sn": "oid_1058IY48",
        "product": [
          {
            "prod_sn": "prid_4386FB59",
            "product": "Rejob",
            "productBrand": "Nestle"
          },
          {
            "prod_sn": "prid_8015VH86",
            "product": "Keytouch",
            "productBrand": "Toyota"
          },
          {
            "prod_sn": "prid_5160XZ11",
            "product": "Strongdax",
            "productBrand": "Volkswagen"
          }
        ],
        "orderType": "cork",
        "amount": 448
      },
      {
        "ord_sn": "oid_7240IA64",
        "product": [
          {
            "prod_sn": "prid_9251KV81",
            "product": "Ice-Dox",
            "productBrand": "Apparel"
          },
          {
            "prod_sn": "prid_0910MD33",
            "product": "Singlelight",
            "productBrand": "Porsche"
          },
          {
            "prod_sn": "prid_8691JY59",
            "product": "Zerlux",
            "productBrand": "Colgate"
          }
        ],
        "orderType": "picture frame",
        "amount": 391
      },
      {
        "ord_sn": "oid_3593IV95",
        "product": [
          {
            "prod_sn": "prid_5135OB46",
            "product": "Grave Zimit",
            "productBrand": "Amazon"
          },
          {
            "prod_sn": "prid_8589CQ78",
            "product": "It Com",
            "productBrand": "Toyota"
          },
          {
            "prod_sn": "prid_4619IQ02",
            "product": "Villa-Flex",
            "productBrand": "Accenture"
          }
        ],
        "orderType": "stockings",
        "amount": 412
      }
    ],
    "phones": {
      "home": "469-55283",
      "mobile": "01797-19076726"
    },
    "address": {
      "personal": {
        "street": "Deuberry Terrace",
        "city": "Maputo",
        "pcode": 34869,
        "country": "Mayotte"
      },
      "work": {
        "workplace": "Dalttechnology Ldt.",
        "jobtitle": "Orthotist and Prosthetist",
        "street": "Lisbon Lane",
        "city": "Taif",
        "pcode": 95239,
        "country": "Thailand",
        "workPhone": "739-77747"
      }
    },
    "about": [
      "wooden",
      "pink",
      "error",
      "juice",
      "wobble",
      "increase",
      "float"
    ],
    "customId": "custId-1566DN87-ap",
    "special": "This value will be returns as is."
  },
  {
    "sn": "5837UC37",
    "login": {
      "username": "fellowshipwander",
      "pass": "BviZP1n+FpKqwEVX",
      "email": "ardelia@outlook.com"
    },
    "title": "Miss",
    "fname": "Mika",
    "lname": "Myslin",
    "photo": "https://randomuser.me/api/portraits/men/88.jpg",
    "orders": [
      {
        "ord_sn": "oid_4148KB50",
        "product": [
          {
            "prod_sn": "prid_0312AC92",
            "product": "It Com",
            "productBrand": "Amazon"
          },
          {
            "prod_sn": "prid_5267HH31",
            "product": "Bluekeyron",
            "productBrand": "Adidas"
          },
          {
            "prod_sn": "prid_9488DB37",
            "product": "Sing-Light",
            "productBrand": "Uniqlo"
          }
        ],
        "orderType": "thermostat",
        "amount": 434
      },
      {
        "ord_sn": "oid_0382KD91",
        "product": [
          {
            "prod_sn": "prid_3991EG42",
            "product": "Tam Rantrax",
            "productBrand": "Netflix"
          },
          {
            "prod_sn": "prid_4822LT12",
            "product": "Dingtouch",
            "productBrand": "Accenture"
          },
          {
            "prod_sn": "prid_8949YB65",
            "product": "Subdox",
            "productBrand": "Cisco"
          }
        ],
        "orderType": "money",
        "amount": 347
      },
      {
        "ord_sn": "oid_8852PF60",
        "product": [
          {
            "prod_sn": "prid_3804BY51",
            "product": "Silfind",
            "productBrand": "McDonald's"
          },
          {
            "prod_sn": "prid_2271LL72",
            "product": "Hotity",
            "productBrand": "Santander"
          },
          {
            "prod_sn": "prid_9099IJ05",
            "product": "Trestostrong",
            "productBrand": "Volkswagen"
          }
        ],
        "orderType": "blanket",
        "amount": 390
      },
      {
        "ord_sn": "oid_3962BX87",
        "product": [
          {
            "prod_sn": "prid_0132HH60",
            "product": "Itcore",
            "productBrand": "HP"
          },
          {
            "prod_sn": "prid_8552UM09",
            "product": "Ecoity",
            "productBrand": "Hermès"
          },
          {
            "prod_sn": "prid_0626CO76",
            "product": "It Lex",
            "productBrand": "Bank of America"
          }
        ],
        "orderType": "twezzers",
        "amount": 409
      }
    ],
    "phones": {
      "home": "451-23478",
      "mobile": "01794-19224634"
    },
    "address": {
      "personal": {
        "street": "Chappells Drive",
        "city": "Zaporizhzhya",
        "pcode": 50601,
        "country": "Pitcairn"
      },
      "work": {
        "workplace": "Treequote Corporation",
        "jobtitle": "Art Director",
        "street": "Dewitt Circle",
        "city": "Yueyang",
        "pcode": 75304,
        "country": "French Guiana",
        "workPhone": "891-23852"
      }
    },
    "about": [
      "punch",
      "unique",
      "linen",
      "bomb",
      "hapless"
    ],
    "customId": "custId-4595AR77-xy",
    "special": "This value will be returns as is."
  },
  {
    "sn": "2246ET41",
    "login": {
      "username": "bonkprophet",
      "pass": "ZnFluRUx5ZHlk7Dt",
      "email": "vulnerableequatorial@outlook.com"
    },
    "title": "Miss",
    "fname": "Rene",
    "lname": "Holdren",
    "photo": "https://randomuser.me/api/portraits/men/27.jpg",
    "orders": [
      {
        "ord_sn": "oid_9836WJ98",
        "product": [
          {
            "prod_sn": "prid_2593WC31",
            "product": "Treslax",
            "productBrand": "L'Oréal"
          },
          {
            "prod_sn": "prid_6646ZP47",
            "product": "K-home",
            "productBrand": "Pepsi"
          },
          {
            "prod_sn": "prid_8596CH36",
            "product": "Sil Is",
            "productBrand": "Lowe's"
          }
        ],
        "orderType": "flag",
        "amount": 468
      },
      {
        "ord_sn": "oid_8109TC18",
        "product": [
          {
            "prod_sn": "prid_3723WQ02",
            "product": "Kinhold",
            "productBrand": "Volkswagen"
          },
          {
            "prod_sn": "prid_5054EH71",
            "product": "Itcore",
            "productBrand": "Chevrolet"
          },
          {
            "prod_sn": "prid_1483BQ02",
            "product": "Rejob",
            "productBrand": "Adobe"
          }
        ],
        "orderType": "pen",
        "amount": 409
      },
      {
        "ord_sn": "oid_6956FL99",
        "product": [
          {
            "prod_sn": "prid_3570KV93",
            "product": "Scotfax",
            "productBrand": "Lexus"
          },
          {
            "prod_sn": "prid_1499HU82",
            "product": "Sailzameco",
            "productBrand": "Gillette"
          },
          {
            "prod_sn": "prid_3453UD36",
            "product": "Silremtex",
            "productBrand": "UPS"
          }
        ],
        "orderType": "sun glasses",
        "amount": 319
      },
      {
        "ord_sn": "oid_0398NH19",
        "product": [
          {
            "prod_sn": "prid_1834EC46",
            "product": "Stocklax",
            "productBrand": "Volkswagen"
          },
          {
            "prod_sn": "prid_1931II43",
            "product": "Cantough",
            "productBrand": "Sony"
          },
          {
            "prod_sn": "prid_0246TO47",
            "product": "Silfind",
            "productBrand": "Amazon"
          }
        ],
        "orderType": "fridge",
        "amount": 311
      }
    ],
    "phones": {
      "home": "730-17698",
      "mobile": "01744-10639996"
    },
    "address": {
      "personal": {
        "street": "Chaparral Drive",
        "city": "Poznan",
        "pcode": 96986,
        "country": "Guinea"
      },
      "work": {
        "workplace": "Ganjaflex Inc.",
        "jobtitle": "Restaurant Cook",
        "street": "Guerard Avenue",
        "city": "Daqing",
        "pcode": 49089,
        "country": "Anguilla",
        "workPhone": "864-22485"
      }
    },
    "about": [
      "duck",
      "loutish",
      "linen",
      "shrill",
      "trains",
      "whole",
      "billowy",
      "bewildered"
    ],
    "customId": "custId-8477SN20-nj",
    "special": "This value will be returns as is."
  },
  {
    "sn": "2935RS30",
    "login": {
      "username": "bikepiercing",
      "pass": "/sWJy/GFAmE-5y3H",
      "email": "glitteringarray@icloud.com"
    },
    "title": "Madam",
    "fname": "Yajaira",
    "lname": "Maragni",
    "photo": "https://randomuser.me/api/portraits/men/26.jpg",
    "orders": [
      {
        "ord_sn": "oid_8075UJ60",
        "product": [
          {
            "prod_sn": "prid_9752WI10",
            "product": "Touchit",
            "productBrand": "Audi"
          },
          {
            "prod_sn": "prid_8808MU20",
            "product": "Stocklax",
            "productBrand": "Accenture"
          },
          {
            "prod_sn": "prid_5031WY13",
            "product": "K-home",
            "productBrand": "Adidas"
          }
        ],
        "orderType": "paper",
        "amount": 357
      },
      {
        "ord_sn": "oid_6467GE08",
        "product": [
          {
            "prod_sn": "prid_0851LH93",
            "product": "Dalttom",
            "productBrand": "Wells Fargo"
          },
          {
            "prod_sn": "prid_9010MI82",
            "product": "Tip-Is",
            "productBrand": "McDonald's"
          },
          {
            "prod_sn": "prid_1668WO08",
            "product": "Airlax",
            "productBrand": "Marlboro"
          }
        ],
        "orderType": "checkbook",
        "amount": 475
      },
      {
        "ord_sn": "oid_4269GD66",
        "product": [
          {
            "prod_sn": "prid_7695DW10",
            "product": "Biotech",
            "productBrand": "Mastercard"
          },
          {
            "prod_sn": "prid_8619SS07",
            "product": "Dongtrax",
            "productBrand": "Nestle"
          },
          {
            "prod_sn": "prid_7405RE46",
            "product": "Kandax",
            "productBrand": "Cisco"
          }
        ],
        "orderType": "picture frame",
        "amount": 456
      },
      {
        "ord_sn": "oid_8409SC17",
        "product": [
          {
            "prod_sn": "prid_9995ZD54",
            "product": "Dongtrax",
            "productBrand": "ESPN"
          },
          {
            "prod_sn": "prid_9114WY66",
            "product": "Stocksing",
            "productBrand": "Oracle"
          },
          {
            "prod_sn": "prid_5981UV87",
            "product": "Fasetam",
            "productBrand": "Citi"
          }
        ],
        "orderType": "charger",
        "amount": 318
      }
    ],
    "phones": {
      "home": "268-19124",
      "mobile": "01730-16567531"
    },
    "address": {
      "personal": {
        "street": "Thistle Court",
        "city": "Bhiwandi",
        "pcode": 85692,
        "country": "Uruguay"
      },
      "work": {
        "workplace": "Ganjaflex Inc.",
        "jobtitle": "Software Developer",
        "street": "Pink Blossom Court",
        "city": "Sihui",
        "pcode": 40684,
        "country": "Syrian Arab Republic",
        "workPhone": "421-46778"
      }
    },
    "about": [
      "hilarious",
      "heartbreaking",
      "hunt",
      "discover",
      "fantastic",
      "cobweb",
      "shock",
      "line"
    ],
    "customId": "custId-1584MY44-xa",
    "special": "This value will be returns as is."
  },
  {
    "sn": "0173HP79",
    "login": {
      "username": "coffinpreach",
      "pass": "*1MAyR2E$Lo1M1RM",
      "email": "guillemette@webmail.de"
    },
    "title": "Miss",
    "fname": "Laurinda",
    "lname": "Desorcy",
    "photo": "https://randomuser.me/api/portraits/men/94.jpg",
    "orders": [
      {
        "ord_sn": "oid_5350CB44",
        "product": [
          {
            "prod_sn": "prid_7559KL44",
            "product": "Solo Randox",
            "productBrand": "John Deere"
          },
          {
            "prod_sn": "prid_1036ET10",
            "product": "Kin Ozecore",
            "productBrand": "Coca-Cola"
          },
          {
            "prod_sn": "prid_3649FN37",
            "product": "Xxx- Ottom",
            "productBrand": "Red Bull"
          }
        ],
        "orderType": "lotion",
        "amount": 349
      },
      {
        "ord_sn": "oid_4950YI94",
        "product": [
          {
            "prod_sn": "prid_1660GG96",
            "product": "Duo Fan",
            "productBrand": "H&M"
          },
          {
            "prod_sn": "prid_6487AA26",
            "product": "Tripplestock",
            "productBrand": "Hermès"
          },
          {
            "prod_sn": "prid_3077FT99",
            "product": "Xxx- Ex",
            "productBrand": "Colgate"
          }
        ],
        "orderType": "checkbook",
        "amount": 329
      },
      {
        "ord_sn": "oid_2147MX92",
        "product": [
          {
            "prod_sn": "prid_3565IH22",
            "product": "Tan-Tip",
            "productBrand": "Telecom"
          },
          {
            "prod_sn": "prid_3509IX32",
            "product": "Silremtex",
            "productBrand": "Coca-Cola"
          },
          {
            "prod_sn": "prid_5242RQ44",
            "product": "Quadlux",
            "productBrand": "Telecom"
          }
        ],
        "orderType": "candy wrapper",
        "amount": 393
      },
      {
        "ord_sn": "oid_6031SO00",
        "product": [
          {
            "prod_sn": "prid_5801EY33",
            "product": "Cofdox",
            "productBrand": "Budweiser"
          },
          {
            "prod_sn": "prid_1844DD98",
            "product": "Cancore",
            "productBrand": "Hyundai"
          },
          {
            "prod_sn": "prid_0187TA81",
            "product": "San Ron",
            "productBrand": "Wells Fargo"
          }
        ],
        "orderType": "perfume",
        "amount": 330
      }
    ],
    "phones": {
      "home": "612-40293",
      "mobile": "01596-14030312"
    },
    "address": {
      "personal": {
        "street": "Willow Brook Lane",
        "city": "Owerri",
        "pcode": 87295,
        "country": "Lesotho"
      },
      "work": {
        "workplace": "Codehow Inc.",
        "jobtitle": "Fabricator",
        "street": "Bonifay Path",
        "city": "Brussels",
        "pcode": 83972,
        "country": "Nepal",
        "workPhone": "777-59960"
      }
    },
    "about": [
      "elite",
      "prick",
      "naive",
      "star"
    ],
    "customId": "custId-2674QZ13-ug",
    "special": "This value will be returns as is."
  },
  {
    "sn": "1539GN61",
    "login": {
      "username": "retireerrol",
      "pass": "xa$tcMbhJ%?W0-u*",
      "email": "argelia@gmx.net"
    },
    "title": "Mr.",
    "fname": "Samuel",
    "lname": "Woolston",
    "photo": "https://randomuser.me/api/portraits/men/33.jpg",
    "orders": [
      {
        "ord_sn": "oid_3152LU69",
        "product": [
          {
            "prod_sn": "prid_1135TY24",
            "product": "Sun-Soft",
            "productBrand": "AT&T"
          },
          {
            "prod_sn": "prid_2308DC60",
            "product": "Stim-Ity",
            "productBrand": "Pepsi"
          },
          {
            "prod_sn": "prid_5535WH25",
            "product": "Tonlex",
            "productBrand": "Citi"
          }
        ],
        "orderType": "chair",
        "amount": 469
      },
      {
        "ord_sn": "oid_5442JT48",
        "product": [
          {
            "prod_sn": "prid_2209JP37",
            "product": "Y-nix",
            "productBrand": "IBM"
          },
          {
            "prod_sn": "prid_2505VC72",
            "product": "K-lax",
            "productBrand": "Cartier"
          },
          {
            "prod_sn": "prid_9179EO50",
            "product": "Keytouch",
            "productBrand": "Microsoft"
          }
        ],
        "orderType": "ice cube tray",
        "amount": 436
      },
      {
        "ord_sn": "oid_7801XR19",
        "product": [
          {
            "prod_sn": "prid_9466LU39",
            "product": "Biotech",
            "productBrand": "Hyundai"
          },
          {
            "prod_sn": "prid_9905WF35",
            "product": "Air Donphase",
            "productBrand": "Verizon"
          },
          {
            "prod_sn": "prid_5994JX09",
            "product": "Treetax",
            "productBrand": "McDonald's"
          }
        ],
        "orderType": "cinder block",
        "amount": 429
      },
      {
        "ord_sn": "oid_8987QW54",
        "product": [
          {
            "prod_sn": "prid_6137BF48",
            "product": "Con Zamdox",
            "productBrand": "Toyota"
          },
          {
            "prod_sn": "prid_3720RX95",
            "product": "Strongdax",
            "productBrand": "Rolex"
          },
          {
            "prod_sn": "prid_9239PM22",
            "product": "Dalttom",
            "productBrand": "Beverages"
          }
        ],
        "orderType": "tv",
        "amount": 464
      }
    ],
    "phones": {
      "home": "877-89594",
      "mobile": "01683-11620423"
    },
    "address": {
      "personal": {
        "street": "El Nino Street",
        "city": "Durgapur",
        "pcode": 30585,
        "country": "Nauru"
      },
      "work": {
        "workplace": "Betatech Enterprises Inc.",
        "jobtitle": "Insurance Sales Agent",
        "street": "Barksdale Drive",
        "city": "Catania",
        "pcode": 52062,
        "country": "Congo",
        "workPhone": "425-51375"
      }
    },
    "about": [
      "wise",
      "graceful",
      "dapper",
      "funny"
    ],
    "customId": "custId-2696KO05-aa",
    "special": "This value will be returns as is."
  },
  {
    "sn": "4371WR35",
    "login": {
      "username": "cowardlydorbel",
      "pass": "yfWHaISOBG$Y1$p4",
      "email": "monorailwholesale@hotmail.com"
    },
    "title": "Mr.",
    "fname": "Charisse",
    "lname": "Featherstone",
    "photo": "https://randomuser.me/api/portraits/men/21.jpg",
    "orders": [
      {
        "ord_sn": "oid_8505EM62",
        "product": [
          {
            "prod_sn": "prid_4647AX98",
            "product": "San Flex",
            "productBrand": "Porsche"
          },
          {
            "prod_sn": "prid_7159TB61",
            "product": "Bionix",
            "productBrand": "Gillette"
          },
          {
            "prod_sn": "prid_1059OE89",
            "product": "Cofdox",
            "productBrand": "Netflix"
          }
        ],
        "orderType": "ipod",
        "amount": 322
      },
      {
        "ord_sn": "oid_9503OQ05",
        "product": [
          {
            "prod_sn": "prid_5765GU73",
            "product": "Ice-Dox",
            "productBrand": "AXA"
          },
          {
            "prod_sn": "prid_8034JW22",
            "product": "Jaystock",
            "productBrand": "Corona"
          },
          {
            "prod_sn": "prid_8635PW72",
            "product": "Temp-Air",
            "productBrand": "ESPN"
          }
        ],
        "orderType": "sandal",
        "amount": 411
      },
      {
        "ord_sn": "oid_1109YU14",
        "product": [
          {
            "prod_sn": "prid_3066LO08",
            "product": "Zim Stock",
            "productBrand": "Pepsi"
          },
          {
            "prod_sn": "prid_0967RR56",
            "product": "Kinlab",
            "productBrand": "Chevrolet"
          },
          {
            "prod_sn": "prid_8596ZH43",
            "product": "Lattax",
            "productBrand": "AT&T"
          }
        ],
        "orderType": "lip gloss",
        "amount": 401
      },
      {
        "ord_sn": "oid_9710SY64",
        "product": [
          {
            "prod_sn": "prid_0931UR39",
            "product": "Big Tip",
            "productBrand": "Deloitte"
          },
          {
            "prod_sn": "prid_5438LU88",
            "product": "Hot Dox",
            "productBrand": "Louis Vuitton"
          },
          {
            "prod_sn": "prid_8065EN56",
            "product": "Trankix",
            "productBrand": "EY"
          }
        ],
        "orderType": "tv",
        "amount": 452
      }
    ],
    "phones": {
      "home": "817-63377",
      "mobile": "01738-19857852"
    },
    "address": {
      "personal": {
        "street": "Boyd Circle",
        "city": "Jixi Heilongjiang",
        "pcode": 63918,
        "country": "Cuba"
      },
      "work": {
        "workplace": "Fasehatice LLC",
        "jobtitle": "Marketing Manager",
        "street": "Bell Terrace",
        "city": "Santa Marta",
        "pcode": 44711,
        "country": "Antigua and Barbuda",
        "workPhone": "121-23321"
      }
    },
    "about": [
      "short",
      "observant",
      "transport",
      "ruthless",
      "concerned",
      "camp",
      "punch",
      "steel"
    ],
    "customId": "custId-0016PH58-rc",
    "special": "This value will be returns as is."
  },
  {
    "sn": "1212NF80",
    "login": {
      "username": "realizeanimagus",
      "pass": "b6xs?d1OX~E/Og-n",
      "email": "asuncion.novy@mail.com"
    },
    "title": "Maid",
    "fname": "Damien",
    "lname": "Kounovsky",
    "photo": "https://randomuser.me/api/portraits/men/76.jpg",
    "orders": [
      {
        "ord_sn": "oid_7183JB29",
        "product": [
          {
            "prod_sn": "prid_6563PD53",
            "product": "Grave Zimit",
            "productBrand": "T-Mobile"
          },
          {
            "prod_sn": "prid_6270FL02",
            "product": "Icestrong",
            "productBrand": "Cartier"
          },
          {
            "prod_sn": "prid_0014BK58",
            "product": "Toughtondex",
            "productBrand": "IBM"
          }
        ],
        "orderType": "picture frame",
        "amount": 315
      },
      {
        "ord_sn": "oid_6070QB80",
        "product": [
          {
            "prod_sn": "prid_3259CI36",
            "product": "Fasetam",
            "productBrand": "Danone"
          },
          {
            "prod_sn": "prid_3697XJ42",
            "product": "Grave Zimit",
            "productBrand": "John Deere"
          },
          {
            "prod_sn": "prid_3494DK56",
            "product": "Konsing",
            "productBrand": "Intel"
          }
        ],
        "orderType": "sharpie",
        "amount": 488
      },
      {
        "ord_sn": "oid_8390SK23",
        "product": [
          {
            "prod_sn": "prid_1276TP02",
            "product": "Kinhold",
            "productBrand": "Beverages"
          },
          {
            "prod_sn": "prid_5503WZ91",
            "product": "Sonnix",
            "productBrand": "Frito-Lay"
          },
          {
            "prod_sn": "prid_5768NZ20",
            "product": "Haydox",
            "productBrand": "Verizon"
          }
        ],
        "orderType": "zipper",
        "amount": 314
      },
      {
        "ord_sn": "oid_4039UK44",
        "product": [
          {
            "prod_sn": "prid_5927FU34",
            "product": "Silstrong",
            "productBrand": "Disney"
          },
          {
            "prod_sn": "prid_2072ES14",
            "product": "Spandom",
            "productBrand": "Lowe's"
          },
          {
            "prod_sn": "prid_6242QO76",
            "product": "Tip-Is",
            "productBrand": "Caterpillar"
          }
        ],
        "orderType": "shawl",
        "amount": 400
      }
    ],
    "phones": {
      "home": "641-21907",
      "mobile": "01605-14899112"
    },
    "address": {
      "personal": {
        "street": "Cedar Grove Loop",
        "city": "Leiyang",
        "pcode": 57978,
        "country": "Bermuda"
      },
      "work": {
        "workplace": "Soylent Corp.",
        "jobtitle": "High School Teacher",
        "street": "Long Loop",
        "city": "Shaoyang",
        "pcode": 14432,
        "country": "Western Sahara",
        "workPhone": "523-21131"
      }
    },
    "about": [
      "rings",
      "bubble",
      "advise",
      "harass",
      "ahead",
      "nod",
      "future",
      "diligent"
    ],
    "customId": "custId-1794TN44-zx",
    "special": "This value will be returns as is."
  },
  {
    "sn": "1079CR16",
    "login": {
      "username": "webbedbillowy",
      "pass": "PbLyehs~2DTe%ZHL",
      "email": "gapingbull@live.com"
    },
    "title": "Mr.",
    "fname": "Leon",
    "lname": "Shehane",
    "photo": "https://randomuser.me/api/portraits/men/63.jpg",
    "orders": [
      {
        "ord_sn": "oid_1608ZY01",
        "product": [
          {
            "prod_sn": "prid_4017GY39",
            "product": "Latbam",
            "productBrand": "Pepsi"
          },
          {
            "prod_sn": "prid_7014KN73",
            "product": "Movefix",
            "productBrand": "Marlboro"
          },
          {
            "prod_sn": "prid_7884LH15",
            "product": "Key-Fax",
            "productBrand": "Verizon"
          }
        ],
        "orderType": "fake flowers",
        "amount": 322
      },
      {
        "ord_sn": "oid_0024IS58",
        "product": [
          {
            "prod_sn": "prid_1155GB14",
            "product": "Jay La",
            "productBrand": "Hennessy"
          },
          {
            "prod_sn": "prid_6022QT00",
            "product": "Alphait",
            "productBrand": "Gucci"
          },
          {
            "prod_sn": "prid_8234RJ67",
            "product": "Triofresh",
            "productBrand": "ESPN"
          }
        ],
        "orderType": "phone",
        "amount": 455
      },
      {
        "ord_sn": "oid_9153NV99",
        "product": [
          {
            "prod_sn": "prid_1812KW92",
            "product": "Konk Ron",
            "productBrand": "SAP"
          },
          {
            "prod_sn": "prid_5679BT42",
            "product": "Trankix",
            "productBrand": "AXA"
          },
          {
            "prod_sn": "prid_9893ZM12",
            "product": "Sub-Lam",
            "productBrand": "Zara"
          }
        ],
        "orderType": "knife",
        "amount": 444
      },
      {
        "ord_sn": "oid_4235BT74",
        "product": [
          {
            "prod_sn": "prid_5018JC24",
            "product": "Haydox",
            "productBrand": "Santander"
          },
          {
            "prod_sn": "prid_7489BI67",
            "product": "Goldenstrong",
            "productBrand": "Marlboro"
          },
          {
            "prod_sn": "prid_3321VZ01",
            "product": "K-lax",
            "productBrand": "Accenture"
          }
        ],
        "orderType": "thermometer",
        "amount": 316
      }
    ],
    "phones": {
      "home": "138-99052",
      "mobile": "01798-16278875"
    },
    "address": {
      "personal": {
        "street": "Bolivar Street",
        "city": "Qiqihaer",
        "pcode": 96821,
        "country": "Mauritius"
      },
      "work": {
        "workplace": "Streethex LLC",
        "jobtitle": "Marketing Manager",
        "street": "Scarboro Court",
        "city": "Huainan",
        "pcode": 29190,
        "country": "Congo",
        "workPhone": "631-11812"
      }
    },
    "about": [
      "ruthless",
      "gabby",
      "null",
      "arrest",
      "vase",
      "elite",
      "afternoon",
      "church"
    ],
    "customId": "custId-7375BJ22-eb",
    "special": "This value will be returns as is."
  },
  {
    "sn": "6739TU85",
    "login": {
      "username": "poopproducer",
      "pass": "2T##eZYBj037ZWnI",
      "email": "libraryjumper@icloud.com"
    },
    "title": "Ms.",
    "fname": "Evette",
    "lname": "Lonas",
    "photo": "https://randomuser.me/api/portraits/men/38.jpg",
    "orders": [
      {
        "ord_sn": "oid_1526QA56",
        "product": [
          {
            "prod_sn": "prid_5671GE53",
            "product": "Ithotfan",
            "productBrand": "Amazon"
          },
          {
            "prod_sn": "prid_6203BZ23",
            "product": "Alpha Apwarm",
            "productBrand": "Uniqlo"
          },
          {
            "prod_sn": "prid_4083LH01",
            "product": "Faxsololux",
            "productBrand": "Hermès"
          }
        ],
        "orderType": "blouse",
        "amount": 308
      },
      {
        "ord_sn": "oid_6143PU65",
        "product": [
          {
            "prod_sn": "prid_3954WA04",
            "product": "Lexitone",
            "productBrand": "Samsung"
          },
          {
            "prod_sn": "prid_5365WE86",
            "product": "Rank Joyla",
            "productBrand": "Goldman Sachs"
          },
          {
            "prod_sn": "prid_9298LH43",
            "product": "Stim-Ity",
            "productBrand": "Lowe's"
          }
        ],
        "orderType": "television",
        "amount": 452
      },
      {
        "ord_sn": "oid_6270DK12",
        "product": [
          {
            "prod_sn": "prid_8658AM86",
            "product": "Openlab",
            "productBrand": "Honda"
          },
          {
            "prod_sn": "prid_8629GM40",
            "product": "Cananlam",
            "productBrand": "Santander"
          },
          {
            "prod_sn": "prid_2625BQ22",
            "product": "Sing Zuntrax",
            "productBrand": "Burger King"
          }
        ],
        "orderType": "money",
        "amount": 373
      },
      {
        "ord_sn": "oid_6647FJ58",
        "product": [
          {
            "prod_sn": "prid_3192GT37",
            "product": "Zoom-Tip",
            "productBrand": "Mastercard"
          },
          {
            "prod_sn": "prid_5774XW80",
            "product": "Ontolight",
            "productBrand": "UBS"
          },
          {
            "prod_sn": "prid_6569WF55",
            "product": "Mathdom",
            "productBrand": "Bank of America"
          }
        ],
        "orderType": "milk",
        "amount": 416
      }
    ],
    "phones": {
      "home": "209-44372",
      "mobile": "01503-19141606"
    },
    "address": {
      "personal": {
        "street": "Olympia Street",
        "city": "Kikwit",
        "pcode": 66138,
        "country": "Malaysia"
      },
      "work": {
        "workplace": "Codehow Inc.",
        "jobtitle": "Business Operations Manager",
        "street": "Elgin Street",
        "city": "Toronto",
        "pcode": 49373,
        "country": "Japan",
        "workPhone": "839-76298"
      }
    },
    "about": [
      "wall",
      "puny",
      "flood"
    ],
    "customId": "custId-3839WV05-ss",
    "special": "This value will be returns as is."
  },
  {
    "sn": "9869HR82",
    "login": {
      "username": "insidiouslate",
      "pass": "B6VtX+-3663WRe3v",
      "email": "delana@hotmail.com"
    },
    "title": "Mr.",
    "fname": "Orville",
    "lname": "Hanawalt",
    "photo": "https://randomuser.me/api/portraits/men/02.jpg",
    "orders": [
      {
        "ord_sn": "oid_8069UD43",
        "product": [
          {
            "prod_sn": "prid_4905GJ43",
            "product": "Airlax",
            "productBrand": "Wells Fargo"
          },
          {
            "prod_sn": "prid_6085BK48",
            "product": "Sumzap",
            "productBrand": "IBM"
          },
          {
            "prod_sn": "prid_1912RN74",
            "product": "Keytouch",
            "productBrand": "Burger King"
          }
        ],
        "orderType": "bag",
        "amount": 353
      },
      {
        "ord_sn": "oid_4342FS16",
        "product": [
          {
            "prod_sn": "prid_3043QZ12",
            "product": "Jaytam",
            "productBrand": "Toyota"
          },
          {
            "prod_sn": "prid_7753BA01",
            "product": "Zamtip",
            "productBrand": "American Express"
          },
          {
            "prod_sn": "prid_9492CY39",
            "product": "Icestrong",
            "productBrand": "John Deere"
          }
        ],
        "orderType": "street lights",
        "amount": 500
      },
      {
        "ord_sn": "oid_6064QU40",
        "product": [
          {
            "prod_sn": "prid_3944RL87",
            "product": "Statity",
            "productBrand": "PayPal"
          },
          {
            "prod_sn": "prid_3827SG58",
            "product": "Tandax",
            "productBrand": "J.P. Morgan"
          },
          {
            "prod_sn": "prid_4190BR60",
            "product": "Zotfinlux",
            "productBrand": "HSBC"
          }
        ],
        "orderType": "cd",
        "amount": 396
      },
      {
        "ord_sn": "oid_0867NZ85",
        "product": [
          {
            "prod_sn": "prid_8854QL21",
            "product": "Phys-Top",
            "productBrand": "Red Bull"
          },
          {
            "prod_sn": "prid_0116HT36",
            "product": "Tam Rantrax",
            "productBrand": "PayPal"
          },
          {
            "prod_sn": "prid_5598VD35",
            "product": "Year Jaystring",
            "productBrand": "John Deere"
          }
        ],
        "orderType": "clay pot",
        "amount": 417
      }
    ],
    "phones": {
      "home": "787-73681",
      "mobile": "01796-10827899"
    },
    "address": {
      "personal": {
        "street": "Ellis Street",
        "city": "Bergamo",
        "pcode": 94864,
        "country": "Luxembourg"
      },
      "work": {
        "workplace": "Dalttechnology Ldt.",
        "jobtitle": "Executive Assistant",
        "street": "Pine Hills Place",
        "city": "Be'er Sheva",
        "pcode": 53636,
        "country": "Tunisia",
        "workPhone": "609-86531"
      }
    },
    "about": [
      "attraction",
      "sparkling",
      "stranger",
      "rail",
      "well-made",
      "chop",
      "fascinated"
    ],
    "customId": "custId-4224II33-kt",
    "special": "This value will be returns as is."
  },
  {
    "sn": "8819ER17",
    "login": {
      "username": "pittertiler",
      "pass": "vHe3/?1$?WtT2A3o",
      "email": "selina@mail.com"
    },
    "title": "Maid",
    "fname": "Manie",
    "lname": "Munos",
    "photo": "https://randomuser.me/api/portraits/men/62.jpg",
    "orders": [
      {
        "ord_sn": "oid_1450OK65",
        "product": [
          {
            "prod_sn": "prid_9851GE94",
            "product": "Tripple-Core",
            "productBrand": "J.P. Morgan"
          },
          {
            "prod_sn": "prid_2108UB50",
            "product": "Ozer-Nix",
            "productBrand": "Adidas"
          },
          {
            "prod_sn": "prid_5853FV41",
            "product": "Quosing",
            "productBrand": "Corona"
          }
        ],
        "orderType": "shampoo",
        "amount": 347
      },
      {
        "ord_sn": "oid_7049DR89",
        "product": [
          {
            "prod_sn": "prid_2653BE53",
            "product": "Homeing",
            "productBrand": "Goldman Sachs"
          },
          {
            "prod_sn": "prid_1554RC13",
            "product": "Staning",
            "productBrand": "BMW"
          },
          {
            "prod_sn": "prid_4996BZ15",
            "product": "Alphawarm",
            "productBrand": "Cisco"
          }
        ],
        "orderType": "sharpie",
        "amount": 385
      },
      {
        "ord_sn": "oid_5267FJ58",
        "product": [
          {
            "prod_sn": "prid_1906DG56",
            "product": "Goldcore",
            "productBrand": "Automotive"
          },
          {
            "prod_sn": "prid_8283GS86",
            "product": "Faxlam",
            "productBrand": "Microsoft"
          },
          {
            "prod_sn": "prid_5941OU07",
            "product": "Jayzamdex",
            "productBrand": "Chevrolet"
          }
        ],
        "orderType": "grid paper",
        "amount": 371
      },
      {
        "ord_sn": "oid_5834WJ23",
        "product": [
          {
            "prod_sn": "prid_6285PS26",
            "product": "Statity",
            "productBrand": "Business Services"
          },
          {
            "prod_sn": "prid_6191JM85",
            "product": "Jaytech",
            "productBrand": "Beverages"
          },
          {
            "prod_sn": "prid_3247OP80",
            "product": "Rank Tough",
            "productBrand": "Apparel"
          }
        ],
        "orderType": "sandal",
        "amount": 376
      }
    ],
    "phones": {
      "home": "651-89239",
      "mobile": "01770-11053337"
    },
    "address": {
      "personal": {
        "street": "Inlet Court",
        "city": "Uvira",
        "pcode": 47315,
        "country": "Rwanda"
      },
      "work": {
        "workplace": "Rangreen Ldt.",
        "jobtitle": "Nurse Anesthetist",
        "street": "Orchid Street",
        "city": "Renqiu",
        "pcode": 61550,
        "country": "Chad",
        "workPhone": "780-77505"
      }
    },
    "about": [
      "clean",
      "ruthless",
      "shut"
    ],
    "customId": "custId-9004JC32-mi",
    "special": "This value will be returns as is."
  },
  {
    "sn": "5216WO00",
    "login": {
      "username": "towbarter",
      "pass": "Y%EB8#3me*fYRq3C",
      "email": "horn@outlook.com"
    },
    "title": "Miss",
    "fname": "Susy",
    "lname": "Debenedetto",
    "photo": "https://randomuser.me/api/portraits/men/41.jpg",
    "orders": [
      {
        "ord_sn": "oid_0118EK54",
        "product": [
          {
            "prod_sn": "prid_4077LM43",
            "product": "Ontolight",
            "productBrand": "John Deere"
          },
          {
            "prod_sn": "prid_1884HJ27",
            "product": "Tam Rantrax",
            "productBrand": "Nintendo"
          },
          {
            "prod_sn": "prid_0383DL46",
            "product": "Sun-Soft",
            "productBrand": "Telecom"
          }
        ],
        "orderType": "window",
        "amount": 373
      },
      {
        "ord_sn": "oid_4390ML15",
        "product": [
          {
            "prod_sn": "prid_0047PJ45",
            "product": "Stronging",
            "productBrand": "Frito-Lay"
          },
          {
            "prod_sn": "prid_6734GS35",
            "product": "Silhome",
            "productBrand": "Cisco"
          },
          {
            "prod_sn": "prid_6243VD03",
            "product": "Rejob",
            "productBrand": "UBS"
          }
        ],
        "orderType": "hair brush",
        "amount": 483
      },
      {
        "ord_sn": "oid_0591TJ86",
        "product": [
          {
            "prod_sn": "prid_6073ES11",
            "product": "Zerlux",
            "productBrand": "Gucci"
          },
          {
            "prod_sn": "prid_7637XS57",
            "product": "Villa-Flex",
            "productBrand": "CVS"
          },
          {
            "prod_sn": "prid_1204XV96",
            "product": "Trusttom",
            "productBrand": "John Deere"
          }
        ],
        "orderType": "hair tie",
        "amount": 485
      },
      {
        "ord_sn": "oid_4405EV22",
        "product": [
          {
            "prod_sn": "prid_3406EI87",
            "product": "Bionix",
            "productBrand": "John Deere"
          },
          {
            "prod_sn": "prid_0118FE34",
            "product": "Singledonphase",
            "productBrand": "Siemens"
          },
          {
            "prod_sn": "prid_6064GQ97",
            "product": "Triofresh",
            "productBrand": "Visa"
          }
        ],
        "orderType": "checkbook",
        "amount": 400
      }
    ],
    "phones": {
      "home": "477-90295",
      "mobile": "01550-16594960"
    },
    "address": {
      "personal": {
        "street": "Trinity Place",
        "city": "Arequipa",
        "pcode": 77117,
        "country": "Nicaragua"
      },
      "work": {
        "workplace": "Donware",
        "jobtitle": "Cost Estimator",
        "street": "Tarrson Blvd.",
        "city": "Liupanshui",
        "pcode": 31182,
        "country": "Solomon Islands",
        "workPhone": "598-96712"
      }
    },
    "about": [
      "guiltless",
      "optimal",
      "push"
    ],
    "customId": "custId-0246EO45-uc",
    "special": "This value will be returns as is."
  },
  {
    "sn": "3955VU37",
    "login": {
      "username": "elateddeceive",
      "pass": "BeK?1GdTwyZZ14U9",
      "email": "mewsnerve@gmail.com"
    },
    "title": "Ms.",
    "fname": "Nenita",
    "lname": "Schreifels",
    "photo": "https://randomuser.me/api/portraits/men/05.jpg",
    "orders": [
      {
        "ord_sn": "oid_1343VY15",
        "product": [
          {
            "prod_sn": "prid_1349KH32",
            "product": "Tranredstrong",
            "productBrand": "Fox"
          },
          {
            "prod_sn": "prid_7638US48",
            "product": "Silremtex",
            "productBrand": "Mastercard"
          },
          {
            "prod_sn": "prid_2741DD54",
            "product": "Fasetam",
            "productBrand": "Disney"
          }
        ],
        "orderType": "sofa",
        "amount": 315
      },
      {
        "ord_sn": "oid_2507GJ49",
        "product": [
          {
            "prod_sn": "prid_2026CP54",
            "product": "Freshjob",
            "productBrand": "Frito-Lay"
          },
          {
            "prod_sn": "prid_3497BV59",
            "product": "Plus Traxnix",
            "productBrand": "Coca-Cola"
          },
          {
            "prod_sn": "prid_1664IJ57",
            "product": "Zerlux",
            "productBrand": "Danone"
          }
        ],
        "orderType": "mouse pad",
        "amount": 348
      },
      {
        "ord_sn": "oid_3716TR09",
        "product": [
          {
            "prod_sn": "prid_1648VU54",
            "product": "Alphaphase",
            "productBrand": "Marlboro"
          },
          {
            "prod_sn": "prid_9344DL64",
            "product": "Xxx- Ottom",
            "productBrand": "Starbucks"
          },
          {
            "prod_sn": "prid_5522VT03",
            "product": "Treetax",
            "productBrand": "J.P. Morgan"
          }
        ],
        "orderType": "scotch tape",
        "amount": 309
      },
      {
        "ord_sn": "oid_9225VA53",
        "product": [
          {
            "prod_sn": "prid_9003FQ08",
            "product": "K-home",
            "productBrand": "Apparel"
          },
          {
            "prod_sn": "prid_5264BS37",
            "product": "Stringfind",
            "productBrand": "Intel"
          },
          {
            "prod_sn": "prid_8314VV26",
            "product": "Homebam",
            "productBrand": "LEGO"
          }
        ],
        "orderType": "apple",
        "amount": 386
      }
    ],
    "phones": {
      "home": "199-10724",
      "mobile": "01750-12225831"
    },
    "address": {
      "personal": {
        "street": "La Quinta Place",
        "city": "San Jose",
        "pcode": 21873,
        "country": "Monaco"
      },
      "work": {
        "workplace": "Plexzap Corp.",
        "jobtitle": "Survey Researcher",
        "street": "Grovewood Place",
        "city": "Guatemala City",
        "pcode": 18281,
        "country": "Bermuda",
        "workPhone": "798-70357"
      }
    },
    "about": [
      "delicate",
      "spring",
      "copy",
      "typical",
      "rings",
      "important",
      "smoke",
      "guiltless"
    ],
    "customId": "custId-7498UT61-wr",
    "special": "This value will be returns as is."
  },
  {
    "sn": "1815KA86",
    "login": {
      "username": "waitpolyjuice",
      "pass": "9ues2?H7~gpgXIrE",
      "email": "vivian@gmail.com"
    },
    "title": "Madam",
    "fname": "Glennie",
    "lname": "Velez",
    "photo": "https://randomuser.me/api/portraits/men/48.jpg",
    "orders": [
      {
        "ord_sn": "oid_0413CR08",
        "product": [
          {
            "prod_sn": "prid_2390OV15",
            "product": "Sing-Light",
            "productBrand": "Gillette"
          },
          {
            "prod_sn": "prid_5284RL91",
            "product": "Icestrong",
            "productBrand": "HP"
          },
          {
            "prod_sn": "prid_7951EI26",
            "product": "Homeing",
            "productBrand": "Nescafe"
          }
        ],
        "orderType": "keyboard",
        "amount": 374
      },
      {
        "ord_sn": "oid_0204PO85",
        "product": [
          {
            "prod_sn": "prid_6035JQ82",
            "product": "Soldax",
            "productBrand": "Gucci"
          },
          {
            "prod_sn": "prid_8842UW77",
            "product": "Con Zamdox",
            "productBrand": "Ford"
          },
          {
            "prod_sn": "prid_0948JO45",
            "product": "It Com",
            "productBrand": "Coca-Cola"
          }
        ],
        "orderType": "magnet",
        "amount": 318
      },
      {
        "ord_sn": "oid_1812ZK15",
        "product": [
          {
            "prod_sn": "prid_2169JX25",
            "product": "Statity",
            "productBrand": "SAP"
          },
          {
            "prod_sn": "prid_1489ZV25",
            "product": "Tampwarm",
            "productBrand": "PwC"
          },
          {
            "prod_sn": "prid_0102HF20",
            "product": "Big Tip",
            "productBrand": "Rolex"
          }
        ],
        "orderType": "box",
        "amount": 438
      },
      {
        "ord_sn": "oid_1384QA70",
        "product": [
          {
            "prod_sn": "prid_6075ST18",
            "product": "Trust Traxlex",
            "productBrand": "Starbucks"
          },
          {
            "prod_sn": "prid_3086FS62",
            "product": "Top-Bam",
            "productBrand": "Coca-Cola"
          },
          {
            "prod_sn": "prid_7738IX25",
            "product": "Dongtrax",
            "productBrand": "Disney"
          }
        ],
        "orderType": "charger",
        "amount": 418
      }
    ],
    "phones": {
      "home": "221-85853",
      "mobile": "01748-12686046"
    },
    "address": {
      "personal": {
        "street": "Larkwood Court",
        "city": "Shaoxing",
        "pcode": 13798,
        "country": "Ukraine"
      },
      "work": {
        "workplace": "Sonron AG",
        "jobtitle": "Chiropractor",
        "street": "Enright Place",
        "city": "London",
        "pcode": 35851,
        "country": "Ghana",
        "workPhone": "686-83812"
      }
    },
    "about": [
      "jittery",
      "burn",
      "lock",
      "stain",
      "elated",
      "approve",
      "guiltless"
    ],
    "customId": "custId-6705ZY47-rw",
    "special": "This value will be returns as is."
  },
  {
    "sn": "7438KQ52",
    "login": {
      "username": "japanlollipop",
      "pass": "jh!72m~$EWbXkffY",
      "email": "francoise@gmail.com"
    },
    "title": "Ms.",
    "fname": "Sophia",
    "lname": "Kakeh",
    "photo": "https://randomuser.me/api/portraits/men/86.jpg",
    "orders": [
      {
        "ord_sn": "oid_5976OM52",
        "product": [
          {
            "prod_sn": "prid_8743JV83",
            "product": "Solozennix",
            "productBrand": "Toyota"
          },
          {
            "prod_sn": "prid_2245XS07",
            "product": "Dripwarm",
            "productBrand": "Adobe"
          },
          {
            "prod_sn": "prid_2728JH85",
            "product": "Sing Zuntrax",
            "productBrand": "Colgate"
          }
        ],
        "orderType": "milk",
        "amount": 438
      },
      {
        "ord_sn": "oid_7326FN49",
        "product": [
          {
            "prod_sn": "prid_5289SK45",
            "product": "Ecoity",
            "productBrand": "Business Services"
          },
          {
            "prod_sn": "prid_6682BU06",
            "product": "Keytouch",
            "productBrand": "Adobe"
          },
          {
            "prod_sn": "prid_6770XW50",
            "product": "Tempfax",
            "productBrand": "Beverages"
          }
        ],
        "orderType": "table",
        "amount": 482
      },
      {
        "ord_sn": "oid_7880HV49",
        "product": [
          {
            "prod_sn": "prid_2629TU82",
            "product": "Lamlab",
            "productBrand": "Chevrolet"
          },
          {
            "prod_sn": "prid_6910BL91",
            "product": "Stanex",
            "productBrand": "Budweiser"
          },
          {
            "prod_sn": "prid_0605QZ53",
            "product": "Tranlex",
            "productBrand": "Allianz"
          }
        ],
        "orderType": "water bottle",
        "amount": 447
      },
      {
        "ord_sn": "oid_0683QZ86",
        "product": [
          {
            "prod_sn": "prid_6456CO84",
            "product": "Plus Traxnix",
            "productBrand": "McDonald's"
          },
          {
            "prod_sn": "prid_6879CL41",
            "product": "Tan-Tip",
            "productBrand": "EY"
          },
          {
            "prod_sn": "prid_7359JT52",
            "product": "Rejob",
            "productBrand": "Visa"
          }
        ],
        "orderType": "food",
        "amount": 358
      }
    ],
    "phones": {
      "home": "695-91342",
      "mobile": "01728-13835001"
    },
    "address": {
      "personal": {
        "street": "Foxwood Lane",
        "city": "Gwangju",
        "pcode": 82540,
        "country": "Palestine, State of"
      },
      "work": {
        "workplace": "Ganjaflex Inc.",
        "jobtitle": "Child and Family Social Worker",
        "street": "Calgary Street",
        "city": "Thrissur",
        "pcode": 82346,
        "country": "Togo",
        "workPhone": "760-23874"
      }
    },
    "about": [
      "steel",
      "foot",
      "shy",
      "shocking",
      "unbiased",
      "educate",
      "yarn"
    ],
    "customId": "custId-2029VI65-nr",
    "special": "This value will be returns as is."
  },
  {
    "sn": "7125FR42",
    "login": {
      "username": "assignmentdiscount",
      "pass": "F#fx2eamGGerNuis",
      "email": "mitchell.sherbert@live.com"
    },
    "title": "Miss",
    "fname": "Taryn",
    "lname": "Umnus",
    "photo": "https://randomuser.me/api/portraits/men/54.jpg",
    "orders": [
      {
        "ord_sn": "oid_2708NW76",
        "product": [
          {
            "prod_sn": "prid_6938BL09",
            "product": "Geocore",
            "productBrand": "American Express"
          },
          {
            "prod_sn": "prid_8036EZ00",
            "product": "Tinwarm",
            "productBrand": "Heineken"
          },
          {
            "prod_sn": "prid_7589PH75",
            "product": "Joyron",
            "productBrand": "Zara"
          }
        ],
        "orderType": "plate",
        "amount": 357
      },
      {
        "ord_sn": "oid_4163XX69",
        "product": [
          {
            "prod_sn": "prid_9846ZO30",
            "product": "Sumzap",
            "productBrand": "KFC"
          },
          {
            "prod_sn": "prid_0255KQ13",
            "product": "Tan-Tip",
            "productBrand": "AXA"
          },
          {
            "prod_sn": "prid_2399FX69",
            "product": "Cofdox",
            "productBrand": "Goldman Sachs"
          }
        ],
        "orderType": "chair",
        "amount": 471
      },
      {
        "ord_sn": "oid_7367NA55",
        "product": [
          {
            "prod_sn": "prid_5088JV21",
            "product": "Lam Hotwarm",
            "productBrand": "Nestle"
          },
          {
            "prod_sn": "prid_7985IA57",
            "product": "Jaystock",
            "productBrand": "John Deere"
          },
          {
            "prod_sn": "prid_6880YJ50",
            "product": "Tres Sing",
            "productBrand": "EY"
          }
        ],
        "orderType": "carrots",
        "amount": 491
      },
      {
        "ord_sn": "oid_7844QR29",
        "product": [
          {
            "prod_sn": "prid_7942NM00",
            "product": "Airlax",
            "productBrand": "Hennessy"
          },
          {
            "prod_sn": "prid_9491TF04",
            "product": "Cantough",
            "productBrand": "Starbucks"
          },
          {
            "prod_sn": "prid_3172ET85",
            "product": "Holdex",
            "productBrand": "ESPN"
          }
        ],
        "orderType": "remote",
        "amount": 440
      }
    ],
    "phones": {
      "home": "382-30336",
      "mobile": "01719-12280216"
    },
    "address": {
      "personal": {
        "street": "Sherwood Street",
        "city": "Coimbatore",
        "pcode": 59683,
        "country": "Ethiopia"
      },
      "work": {
        "workplace": "Gogozoom",
        "jobtitle": "Art Director",
        "street": "Greg Terrace",
        "city": "Kolkata",
        "pcode": 59095,
        "country": "Guinea",
        "workPhone": "234-96477"
      }
    },
    "about": [
      "mine",
      "group",
      "loaf",
      "flood",
      "obscene",
      "bite",
      "cagey"
    ],
    "customId": "custId-9434RL99-lc",
    "special": "This value will be returns as is."
  },
  {
    "sn": "8932HF57",
    "login": {
      "username": "ickymammary",
      "pass": "xT4uMkRQnV%7ykvA",
      "email": "beastmillwright@gmail.com"
    },
    "title": "Maid",
    "fname": "Kyung",
    "lname": "Viel",
    "photo": "https://randomuser.me/api/portraits/men/25.jpg",
    "orders": [
      {
        "ord_sn": "oid_1576FX35",
        "product": [
          {
            "prod_sn": "prid_2937FK62",
            "product": "Trusttom",
            "productBrand": "American Express"
          },
          {
            "prod_sn": "prid_8060IQ45",
            "product": "Gravestatwarm",
            "productBrand": "Cisco"
          },
          {
            "prod_sn": "prid_5090IK18",
            "product": "Lamlab",
            "productBrand": "IKEA"
          }
        ],
        "orderType": "chapter book",
        "amount": 382
      },
      {
        "ord_sn": "oid_8304YE88",
        "product": [
          {
            "prod_sn": "prid_1385HO75",
            "product": "Zerlux",
            "productBrand": "Mastercard"
          },
          {
            "prod_sn": "prid_4611OZ08",
            "product": "Volttam",
            "productBrand": "BMW"
          },
          {
            "prod_sn": "prid_1787VL76",
            "product": "Touchit",
            "productBrand": "NIKE"
          }
        ],
        "orderType": "outlet",
        "amount": 434
      },
      {
        "ord_sn": "oid_8482VN88",
        "product": [
          {
            "prod_sn": "prid_4762CJ77",
            "product": "Faxsololux",
            "productBrand": "Frito-Lay"
          },
          {
            "prod_sn": "prid_7768KN51",
            "product": "K-sing",
            "productBrand": "Disney"
          },
          {
            "prod_sn": "prid_5554UW83",
            "product": "Stronging",
            "productBrand": "J.P. Morgan"
          }
        ],
        "orderType": "television",
        "amount": 309
      },
      {
        "ord_sn": "oid_1781TV04",
        "product": [
          {
            "prod_sn": "prid_3951AV37",
            "product": "Jay La",
            "productBrand": "Budweiser"
          },
          {
            "prod_sn": "prid_5633QS61",
            "product": "Faxhold",
            "productBrand": "Wells Fargo"
          },
          {
            "prod_sn": "prid_3632MO64",
            "product": "Solozennix",
            "productBrand": "PayPal"
          }
        ],
        "orderType": "vase",
        "amount": 414
      }
    ],
    "phones": {
      "home": "536-41176",
      "mobile": "01545-17182080"
    },
    "address": {
      "personal": {
        "street": "Opossum Place",
        "city": "Nouakchott",
        "pcode": 58724,
        "country": "Tanzania, United Republic of"
      },
      "work": {
        "workplace": "Jom Jenson Inc.",
        "jobtitle": "Child and Family Social Worker",
        "street": "Almanza Drive",
        "city": "Yerevan",
        "pcode": 27192,
        "country": "Falkland Islands (Malvinas)",
        "workPhone": "786-33183"
      }
    },
    "about": [
      "push",
      "fork",
      "star"
    ],
    "customId": "custId-9509DG81-xo",
    "special": "This value will be returns as is."
  },
  {
    "sn": "0468UP59",
    "login": {
      "username": "bedroomsteer",
      "pass": "EkQV62PJjtyd%ZT2",
      "email": "evelin.fower@gmx.net"
    },
    "title": "Madam",
    "fname": "Aida",
    "lname": "Polimeni",
    "photo": "https://randomuser.me/api/portraits/men/77.jpg",
    "orders": [
      {
        "ord_sn": "oid_7999KV04",
        "product": [
          {
            "prod_sn": "prid_1138GU51",
            "product": "An-Zap",
            "productBrand": "Deloitte"
          },
          {
            "prod_sn": "prid_9253VO40",
            "product": "Cantough",
            "productBrand": "FedEx"
          },
          {
            "prod_sn": "prid_6570JL66",
            "product": "Ice-Dox",
            "productBrand": "McDonald's"
          }
        ],
        "orderType": "sun glasses",
        "amount": 438
      },
      {
        "ord_sn": "oid_7032SZ44",
        "product": [
          {
            "prod_sn": "prid_1474IU74",
            "product": "Faxsololux",
            "productBrand": "KFC"
          },
          {
            "prod_sn": "prid_6250UG81",
            "product": "Rejob",
            "productBrand": "NIKE"
          },
          {
            "prod_sn": "prid_1303DK19",
            "product": "Lotcof",
            "productBrand": "Cisco"
          }
        ],
        "orderType": "tree",
        "amount": 309
      },
      {
        "ord_sn": "oid_7393SS23",
        "product": [
          {
            "prod_sn": "prid_9763NV17",
            "product": "X--Fan",
            "productBrand": "Red Bull"
          },
          {
            "prod_sn": "prid_5705TX06",
            "product": "Goldenstrong",
            "productBrand": "Cisco"
          },
          {
            "prod_sn": "prid_5638EO34",
            "product": "Tonfind",
            "productBrand": "SAP"
          }
        ],
        "orderType": "eye liner",
        "amount": 343
      },
      {
        "ord_sn": "oid_0187RH28",
        "product": [
          {
            "prod_sn": "prid_3303UK88",
            "product": "Unaron",
            "productBrand": "Chevrolet"
          },
          {
            "prod_sn": "prid_9444XE92",
            "product": "Uno Sing",
            "productBrand": "John Deere"
          },
          {
            "prod_sn": "prid_4448RG95",
            "product": "Tranlex",
            "productBrand": "Mercedes-Benz"
          }
        ],
        "orderType": "eraser",
        "amount": 436
      }
    ],
    "phones": {
      "home": "656-21084",
      "mobile": "01760-10759633"
    },
    "address": {
      "personal": {
        "street": "Foster Place",
        "city": "Gebze",
        "pcode": 54479,
        "country": "British Indian Ocean Territory"
      },
      "work": {
        "workplace": "Plusstrip Inc.",
        "jobtitle": "Computer Support Specialist",
        "street": "Frederick Terrace",
        "city": "Denpasar",
        "pcode": 26086,
        "country": "Anguilla",
        "workPhone": "653-58401"
      }
    },
    "about": [
      "belong",
      "short",
      "typical"
    ],
    "customId": "custId-6935AB06-ki",
    "special": "This value will be returns as is."
  },
  {
    "sn": "5930QB22",
    "login": {
      "username": "chilereview",
      "pass": "9AmXo6QtRu0~ISda",
      "email": "heartbeggarly@icloud.com"
    },
    "title": "Mr.",
    "fname": "Shayna",
    "lname": "Rardon",
    "photo": "https://randomuser.me/api/portraits/men/61.jpg",
    "orders": [
      {
        "ord_sn": "oid_8198IE64",
        "product": [
          {
            "prod_sn": "prid_7987RB91",
            "product": "Qvo Eco",
            "productBrand": "Allianz"
          },
          {
            "prod_sn": "prid_5154HM17",
            "product": "Alphait",
            "productBrand": "ESPN"
          },
          {
            "prod_sn": "prid_9481RF11",
            "product": "Geocore",
            "productBrand": "EY"
          }
        ],
        "orderType": "glasses",
        "amount": 414
      },
      {
        "ord_sn": "oid_2549LX28",
        "product": [
          {
            "prod_sn": "prid_5036JF72",
            "product": "Tindom",
            "productBrand": "Sony"
          },
          {
            "prod_sn": "prid_3908II38",
            "product": "Anwarm",
            "productBrand": "Goldman Sachs"
          },
          {
            "prod_sn": "prid_8107EN65",
            "product": "Kaneco",
            "productBrand": "Mastercard"
          }
        ],
        "orderType": "key chain",
        "amount": 374
      },
      {
        "ord_sn": "oid_3019QM23",
        "product": [
          {
            "prod_sn": "prid_8353WI77",
            "product": "Tam Rantrax",
            "productBrand": "IKEA"
          },
          {
            "prod_sn": "prid_9420HV26",
            "product": "Con Zamdox",
            "productBrand": "Mercedes-Benz"
          },
          {
            "prod_sn": "prid_6059JL09",
            "product": "Freshtough",
            "productBrand": "Adobe"
          }
        ],
        "orderType": "lamp",
        "amount": 418
      },
      {
        "ord_sn": "oid_4267HS93",
        "product": [
          {
            "prod_sn": "prid_4240RB11",
            "product": "Alphaphase",
            "productBrand": "Audi"
          },
          {
            "prod_sn": "prid_6189IB22",
            "product": "Faxlam",
            "productBrand": "ESPN"
          },
          {
            "prod_sn": "prid_4332KN16",
            "product": "Topron",
            "productBrand": "Zara"
          }
        ],
        "orderType": "sailboat",
        "amount": 376
      }
    ],
    "phones": {
      "home": "528-69329",
      "mobile": "01522-14835185"
    },
    "address": {
      "personal": {
        "street": "Apollo Lane",
        "city": "Jhansi",
        "pcode": 58146,
        "country": "Nigeria"
      },
      "work": {
        "workplace": "Acme Corporation",
        "jobtitle": "Accountant",
        "street": "Joes Street",
        "city": "Tanta",
        "pcode": 11125,
        "country": "Papua New Guinea",
        "workPhone": "611-79037"
      }
    },
    "about": [
      "detect",
      "bore",
      "wall"
    ],
    "customId": "custId-1741YL73-qv",
    "special": "This value will be returns as is."
  },
  {
    "sn": "2977ZZ14",
    "login": {
      "username": "saxcruciatus",
      "pass": "03Ukb-tEttH~UOp~",
      "email": "morgan.pipia@gmail.com"
    },
    "title": "Maid",
    "fname": "Daysi",
    "lname": "Bostrom",
    "photo": "https://randomuser.me/api/portraits/men/64.jpg",
    "orders": [
      {
        "ord_sn": "oid_2818KJ45",
        "product": [
          {
            "prod_sn": "prid_6409QC21",
            "product": "Tranredstrong",
            "productBrand": "Apparel"
          },
          {
            "prod_sn": "prid_6545KE19",
            "product": "Viva Tolax",
            "productBrand": "Gillette"
          },
          {
            "prod_sn": "prid_4806AJ20",
            "product": "Nim Dox",
            "productBrand": "Hennessy"
          }
        ],
        "orderType": "sharpie",
        "amount": 408
      },
      {
        "ord_sn": "oid_4007CD28",
        "product": [
          {
            "prod_sn": "prid_8538SK44",
            "product": "Grave Zimit",
            "productBrand": "Beverages"
          },
          {
            "prod_sn": "prid_6509XB46",
            "product": "Quosing",
            "productBrand": "Telecom"
          },
          {
            "prod_sn": "prid_2011VQ85",
            "product": "Grave Zimit",
            "productBrand": "PayPal"
          }
        ],
        "orderType": "radio",
        "amount": 490
      },
      {
        "ord_sn": "oid_2815HO72",
        "product": [
          {
            "prod_sn": "prid_3941ZC93",
            "product": "Treetax",
            "productBrand": "Adobe"
          },
          {
            "prod_sn": "prid_5194GU22",
            "product": "Konk Ron",
            "productBrand": "Accenture"
          },
          {
            "prod_sn": "prid_0273NJ91",
            "product": "Jayzamdex",
            "productBrand": "Fox"
          }
        ],
        "orderType": "tomato",
        "amount": 489
      },
      {
        "ord_sn": "oid_7748YZ64",
        "product": [
          {
            "prod_sn": "prid_6312EN80",
            "product": "Spandom",
            "productBrand": "Uniqlo"
          },
          {
            "prod_sn": "prid_0939QN10",
            "product": "Grave Zimit",
            "productBrand": "Wells Fargo"
          },
          {
            "prod_sn": "prid_3371KE89",
            "product": "Sumin",
            "productBrand": "ESPN"
          }
        ],
        "orderType": "radio",
        "amount": 303
      }
    ],
    "phones": {
      "home": "254-91482",
      "mobile": "01760-10103883"
    },
    "address": {
      "personal": {
        "street": "Hiles Place",
        "city": "Marrakech",
        "pcode": 70722,
        "country": "Dominican Republic"
      },
      "work": {
        "workplace": "Ganjaflex Inc.",
        "jobtitle": "Teacher Assistant",
        "street": "Nance Run",
        "city": "Durango",
        "pcode": 37811,
        "country": "Congo, Democratic Republic of the",
        "workPhone": "321-27812"
      }
    },
    "about": [
      "lettuce",
      "clammy",
      "modern",
      "gusty",
      "brave"
    ],
    "customId": "custId-5703BV57-ts",
    "special": "This value will be returns as is."
  },
  {
    "sn": "6141DV39",
    "login": {
      "username": "potentialweary",
      "pass": "SS7$qSX2Jjyfy3#v",
      "email": "sam.ruane@gmail.com"
    },
    "title": "Master",
    "fname": "Clyde",
    "lname": "Mogollon",
    "photo": "https://randomuser.me/api/portraits/men/32.jpg",
    "orders": [
      {
        "ord_sn": "oid_7318SN00",
        "product": [
          {
            "prod_sn": "prid_2794AY55",
            "product": "Is-Sing",
            "productBrand": "FedEx"
          },
          {
            "prod_sn": "prid_4168MG13",
            "product": "Stringfind",
            "productBrand": "HSBC"
          },
          {
            "prod_sn": "prid_7754UQ62",
            "product": "Tranredstrong",
            "productBrand": "Mastercard"
          }
        ],
        "orderType": "truck",
        "amount": 328
      },
      {
        "ord_sn": "oid_5427CB94",
        "product": [
          {
            "prod_sn": "prid_2255HO80",
            "product": "Onto Goit",
            "productBrand": "Mercedes-Benz"
          },
          {
            "prod_sn": "prid_1557CI47",
            "product": "Zerlux",
            "productBrand": "L'Oréal"
          },
          {
            "prod_sn": "prid_1810FB85",
            "product": "Hotity",
            "productBrand": "UPS"
          }
        ],
        "orderType": "desk",
        "amount": 490
      },
      {
        "ord_sn": "oid_6967LV03",
        "product": [
          {
            "prod_sn": "prid_4828DJ63",
            "product": "Subdox",
            "productBrand": "Mercedes-Benz"
          },
          {
            "prod_sn": "prid_3857EE90",
            "product": "Con Zamdox",
            "productBrand": "Pampers"
          },
          {
            "prod_sn": "prid_0080HL32",
            "product": "Air Donphase",
            "productBrand": "Nestle"
          }
        ],
        "orderType": "zipper",
        "amount": 394
      },
      {
        "ord_sn": "oid_0791DF99",
        "product": [
          {
            "prod_sn": "prid_4362YV51",
            "product": "Toughstrong",
            "productBrand": "Marlboro"
          },
          {
            "prod_sn": "prid_2775JO80",
            "product": "Faxhold",
            "productBrand": "FedEx"
          },
          {
            "prod_sn": "prid_4211JD11",
            "product": "Sol Ron",
            "productBrand": "Beverages"
          }
        ],
        "orderType": "seat belt",
        "amount": 364
      }
    ],
    "phones": {
      "home": "457-86095",
      "mobile": "01569-19073934"
    },
    "address": {
      "personal": {
        "street": "Corsair Court",
        "city": "Cuautla Morelos",
        "pcode": 78346,
        "country": "Yemen"
      },
      "work": {
        "workplace": "Jom Jenson Inc.",
        "jobtitle": "Environmental Science and Protection Technician",
        "street": "Aloha Way",
        "city": "Lagos",
        "pcode": 58127,
        "country": "Lebanon",
        "workPhone": "557-87844"
      }
    },
    "about": [
      "penitent",
      "expand",
      "flashy",
      "barbarous",
      "flat",
      "turn",
      "feeling"
    ],
    "customId": "custId-7717NX95-ml",
    "special": "This value will be returns as is."
  }
]